MANIFEST.in
setup.py
dgw/__init__.py
dgw.egg-info/PKG-INFO
dgw.egg-info/SOURCES.txt
dgw.egg-info/dependency_links.txt
dgw.egg-info/entry_points.txt
dgw.egg-info/requires.txt
dgw.egg-info/top_level.txt
dgw/_mlpy/__init__.py
dgw/bin/__init__.py
dgw/bin/explorer.py
dgw/bin/extract_gene_regions.py
dgw/bin/overlaps2poi.py
dgw/bin/prototypes2dot.py
dgw/bin/worker.py
dgw/cli/__init__.py
dgw/cli/actions.py
dgw/cli/configuration.py
dgw/cluster/__init__.py
dgw/cluster/analysis.py
dgw/cluster/visualisation.py
dgw/data/__init__.py
dgw/data/containers.py
dgw/data/parsers/__init__.py
dgw/data/parsers/bam.py
dgw/data/parsers/bed.py
dgw/data/parsers/cpgs.py
dgw/data/parsers/filters.py
dgw/data/parsers/genes.py
dgw/data/parsers/pois.py
dgw/data/visualisation/__init__.py
dgw/data/visualisation/heatmap.py
dgw/dtw/__init__.py
dgw/dtw/distance.py
dgw/dtw/parallel.py
dgw/dtw/scaling.py
dgw/dtw/transformations.py
dgw/dtw/utilities.py
dgw/dtw/visualisation.py
dgw/tests/__init__.py
dgw/tests/data/__init__.py
dgw/tests/data/test_containers.py
dgw/tests/data/parsers/__init__.py
dgw/tests/data/parsers/test_bam.py
dgw/tests/data/parsers/test_filters.py
dgw/tests/dtw/__init__.py
dgw/tests/dtw/test_distance.py
dgw/tests/dtw/test_parallel.py
dgw/tests/dtw/test_transformations.py
mlpy_src/dtw/cdtw.c
mlpy_src/dtw/cdtw.h
mlpy_src/dtw/cdtw.pxd
mlpy_src/dtw/dtw.c
mlpy_src/dtw/dtw.pyx