Metadata-Version: 1.0
Name: dgw
Version: 0.1.1
Summary: Dynamic Genome Warping
Home-page: http://sauliusl.github.com/dgw/
Author: Saulius Lukauskas
Author-email: luksaulius@gmail.com
License: GPLv3
Platform: UNKNOWN
